tadrep/__init__.py
tadrep/blast.py
tadrep/characterize.py
tadrep/cluster.py
tadrep/config.py
tadrep/detect.py
tadrep/extract.py
tadrep/io.py
tadrep/main.py
tadrep/plasmids.py
tadrep/setup.py
tadrep/utils.py
tadrep/visualize.py
tadrep/database/__init__.py
tadrep/database/main.py
tadrep/database/plsdb.py
tadrep/database/refseq.py
tadrep-0.9.2.dist-info/LICENSE
tadrep-0.9.2.dist-info/METADATA
tadrep-0.9.2.dist-info/WHEEL
tadrep-0.9.2.dist-info/entry_points.txt
tadrep-0.9.2.dist-info/top_level.txt
tadrep-0.9.2.dist-info/RECORD
