Metadata-Version: 2.1
Name: tadrep
Version: 0.9.2
Summary: TaDRep: Targeted Detection and Reconstruction of Plasmids
Home-page: https://github.com/oschwengers/tadrep
Author: Oliver Schwengers
Author-email: oliver.schwengers@computational.bio.uni-giessen.de
License: GPLv3
Project-URL: Documentation, https://github.com/oschwengers/tadrep/blob/main/README.md
Project-URL: Source, https://github.com/oschwengers/tadrep
Project-URL: Bug Reports, https://github.com/oschwengers/tadrep/issues
Project-URL: CI, https://github.com/oschwengers/tadrep/actions
Keywords: bioinformatics,bacteria,plasmids
Classifier: Operating System :: POSIX :: Linux
Classifier: Programming Language :: Python :: 3 :: Only
Classifier: Programming Language :: Python :: 3.8
Classifier: Programming Language :: Python :: 3.9
Classifier: Programming Language :: Python :: 3.10
Classifier: Programming Language :: Python :: 3.11
Classifier: Development Status :: 4 - Beta 
Classifier: License :: OSI Approved :: GNU General Public License v3 (GPLv3)
Classifier: Topic :: Scientific/Engineering :: Bio-Informatics
Classifier: Environment :: Console
Classifier: Intended Audience :: Science/Research
Classifier: Natural Language :: English
Requires-Python: >=3.8
License-File: LICENSE
Requires-Dist: biopython >=1.78
Requires-Dist: xopen >=1.5.0
Requires-Dist: pyrodigal >=2.1.0
Requires-Dist: matplotlib >=3.7
Requires-Dist: pygenomeviz >=0.4
